exceptions/__init__.py
exceptions/exceptions.py
Santos-1.0.1.dist-info/RECORD
Santos-1.0.1.dist-info/metadata.json
Santos-1.0.1.dist-info/DESCRIPTION.rst
Santos-1.0.1.dist-info/top_level.txt
Santos-1.0.1.dist-info/WHEEL
Santos-1.0.1.dist-info/METADATA
santos/__init__.py
santos/santos.py
