Metadata-Version: 2.0
Name: Santos
Version: 1.0.1
Summary: A task schedule
Home-page: https://github.com/anderson89marques/Santos
Author: Anderson Marques
Author-email: andersonoanjo18@gmail.com
License: MIT
Keywords: Santos task schedule setuptools development
Platform: UNKNOWN
Classifier: Development Status :: 3 - Alpha
Classifier: Intended Audience :: Developers
Classifier: Topic :: Software Development :: Build Tools
Classifier: License :: OSI Approved :: MIT License
Classifier: Programming Language :: Python :: 2.7
Classifier: Programming Language :: Python :: 3.2
Classifier: Programming Language :: Python :: 3.3
Classifier: Programming Language :: Python :: 3.4
